LittleDog/__init__.py
LittleDog/module.py
LittleDog-0.1.1.dist-info/LICENSE
LittleDog-0.1.1.dist-info/METADATA
LittleDog-0.1.1.dist-info/WHEEL
LittleDog-0.1.1.dist-info/top_level.txt
LittleDog-0.1.1.dist-info/RECORD
