Metadata-Version: 2.1
Name: LittleDog
Version: 0.1.1
Summary: A must have python package which makes pragramming a lot easier
Author-email: Little Dog <littledog.5727@gmail.com>
License: Copyright (c) 2023 Littledog
Project-URL: Homepage, https://www.sites.google.com/view/littledog-python
Project-URL: Download, https://pypi.org/project/Littledog/#files
Project-URL: License, https://github.com/LittleDog5727/littledog-python/blob/main/LICENSE
Project-URL: Repository, https://github.com/LittleDog5727/littledog-python
Classifier: Programming Language :: Python :: 3
Classifier: Operating System :: OS Independent
Requires-Python: >=3.9
License-File: LICENSE
